hssh/DefClass.py
hssh/Kmeans.py
hssh/__init__.py
hssh-0.1.0.dist-info/METADATA
hssh-0.1.0.dist-info/WHEEL
hssh-0.1.0.dist-info/top_level.txt
hssh-0.1.0.dist-info/RECORD
