Metadata-Version: 2.1
Name: hssh
Version: 0.1.0
Summary: 키워드 추출 및 유사도 분석을 위한 hssh 패키지 2702김수진제작
Home-page: https://github.com/Sujin-Github/Study2022
License: UNKNOWN
Platform: UNKNOWN
Requires-Dist: pandas
Requires-Dist: konlpy
Requires-Dist: numpy
